[
    [
        {
            "time": "",
            "original_text": "战投不成，高瓴改道投资子公司曲线“入局”国瓷材料！",
            "features": {
                "keywords": [
                    "高瓴",
                    "国瓷材料",
                    "子公司",
                    "投资"
                ],
                "sentiment_score": 0.6,
                "policy_related": "false",
                "investment_strategy": "true",
                "sector_focus": [
                    "材料"
                ],
                "causal_factor": "true",
                "causal_impact": "positive",
                "affected_by_time_series": "false",
                "ts_effect_direction": ""
            },
            "scores": {
                "Correlation": 9,
                "Sentiment": 7,
                "Importance": 8,
                "Impact": 7,
                "Duration": 4,
                "Entity_Density": 8,
                "Market_Scope": 5,
                "Time_Proximity": 8,
                "Headline_Structure": 7,
                "Source_Recency": 8
            }
        },
        {
            "time": "",
            "original_text": "制造行业日报：石大胜华电池级DMC价格跳涨500元",
            "features": {
                "keywords": [
                    "石大胜华",
                    "DMC",
                    "价格跳涨"
                ],
                "sentiment_score": 0.7,
                "policy_related": "false",
                "investment_strategy": "false",
                "sector_focus": [
                    "化工",
                    "电池材料"
                ],
                "causal_factor": "true",
                "causal_impact": "positive",
                "affected_by_time_series": "true",
                "ts_effect_direction": "positive"
            },
            "scores": {
                "Correlation": 8,
                "Sentiment": 6,
                "Importance": 7,
                "Impact": 6,
                "Duration": 3,
                "Entity_Density": 7,
                "Market_Scope": 6,
                "Time_Proximity": 7,
                "Headline_Structure": 6,
                "Source_Recency": 7
            }
        },
        {
            "time": "",
            "original_text": "陆股通净买入4.39亿元，连续3日净买入",
            "features": {
                "keywords": [
                    "陆股通",
                    "净买入",
                    "连续3日"
                ],
                "sentiment_score": 0.8,
                "policy_related": "false",
                "investment_strategy": "false",
                "sector_focus": [],
                "causal_factor": "true",
                "causal_impact": "positive",
                "affected_by_time_series": "true",
                "ts_effect_direction": "positive"
            },
            "scores": {
                "Correlation": 8,
                "Sentiment": 6,
                "Importance": 6,
                "Impact": 5,
                "Duration": 2,
                "Entity_Density": 6,
                "Market_Scope": 7,
                "Time_Proximity": 8,
                "Headline_Structure": 5,
                "Source_Recency": 8
            }
        },
        {
            "time": "",
            "original_text": "重庆蚂蚁消费金融有限公司获准筹建，蚂蚁集团持股50%",
            "features": {
                "keywords": [
                    "蚂蚁集团",
                    "消费金融",
                    "筹建"
                ],
                "sentiment_score": 0.7,
                "policy_related": "false",
                "investment_strategy": "true",
                "sector_focus": [
                    "金融科技"
                ],
                "causal_factor": "true",
                "causal_impact": "positive",
                "affected_by_time_series": "false",
                "ts_effect_direction": ""
            },
            "scores": {
                "Correlation": 9,
                "Sentiment": 7,
                "Importance": 8,
                "Impact": 7,
                "Duration": 5,
                "Entity_Density": 8,
                "Market_Scope": 5,
                "Time_Proximity": 8,
                "Headline_Structure": 7,
                "Source_Recency": 8
            }
        },
        {
            "time": "",
            "original_text": "硅纳米线、无钴高镍、干电极…特斯拉“电池日”将公布哪些新技术？",
            "features": {
                "keywords": [
                    "特斯拉",
                    "电池日",
                    "新技术"
                ],
                "sentiment_score": 0.8,
                "policy_related": "false",
                "investment_strategy": "false",
                "sector_focus": [
                    "新能源汽车",
                    "电池技术"
                ],
                "causal_factor": "true",
                "causal_impact": "positive",
                "affected_by_time_series": "true",
                "ts_effect_direction": "positive"
            },
            "scores": {
                "Correlation": 8,
                "Sentiment": 6,
                "Importance": 8,
                "Impact": 7,
                "Duration": 6,
                "Entity_Density": 7,
                "Market_Scope": 7,
                "Time_Proximity": 7,
                "Headline_Structure": 7,
                "Source_Recency": 7
            }
        },
        {
            "time": "",
            "original_text": "北上资金净买入4.39亿元宁德时代获净买入3.96亿元",
            "features": {
                "keywords": [
                    "北上资金",
                    "宁德时代",
                    "净买入"
                ],
                "sentiment_score": 0.8,
                "policy_related": "false",
                "investment_strategy": "false",
                "sector_focus": [
                    "新能源汽车",
                    "锂电池"
                ],
                "causal_factor": "true",
                "causal_impact": "positive",
                "affected_by_time_series": "true",
                "ts_effect_direction": "positive"
            },
            "scores": {
                "Correlation": 8,
                "Sentiment": 6,
                "Importance": 7,
                "Impact": 6,
                "Duration": 3,
                "Entity_Density": 7,
                "Market_Scope": 6,
                "Time_Proximity": 8,
                "Headline_Structure": 5,
                "Source_Recency": 8
            }
        },
        {
            "time": "",
            "original_text": "北向资金连续三日净流入，贵州茅台遭外资大幅净卖出21.23亿元",
            "features": {
                "keywords": [
                    "北向资金",
                    "贵州茅台",
                    "净流出"
                ],
                "sentiment_score": -0.7,
                "policy_related": "false",
                "investment_strategy": "false",
                "sector_focus": [
                    "白酒"
                ],
                "causal_factor": "true",
                "causal_impact": "negative",
                "affected_by_time_series": "true",
                "ts_effect_direction": "negative"
            },
            "scores": {
                "Correlation": 8,
                "Sentiment": 5,
                "Importance": 7,
                "Impact": 6,
                "Duration": 4,
                "Entity_Density": 7,
                "Market_Scope": 7,
                "Time_Proximity": 8,
                "Headline_Structure": 6,
                "Source_Recency": 8
            }
        },
        {
            "time": "",
            "original_text": "A股收盘：“喝酒吃肉”概念股集体下跌 贵州茅台收跌超3% 连续下跌",
            "features": {
                "keywords": [
                    "A股",
                    "贵州茅台",
                    "下跌"
                ],
                "sentiment_score": -0.8,
                "policy_related": "false",
                "investment_strategy": "false",
                "sector_focus": [
                    "白酒"
                ],
                "causal_factor": "true",
                "causal_impact": "negative",
                "affected_by_time_series": "true",
                "ts_effect_direction": "negative"
            },
            "scores": {
                "Correlation": 8,
                "Sentiment": 4,
                "Importance": 7,
                "Impact": 6,
                "Duration": 4,
                "Entity_Density": 7,
                "Market_Scope": 7,
                "Time_Proximity": 8,
                "Headline_Structure": 6,
                "Source_Recency": 8
            }
        },
        {
            "time": "",
            "original_text": "宁德时代25亿元增资先导智能 对手比亚迪3天大涨25%",
            "features": {
                "keywords": [
                    "宁德时代",
                    "先导智能",
                    "比亚迪",
                    "增资"
                ],
                "sentiment_score": 0.7,
                "policy_related": "false",
                "investment_strategy": "true",
                "sector_focus": [
                    "新能源汽车",
                    "锂电池"
                ],
                "causal_factor": "true",
                "causal_impact": "positive",
                "affected_by_time_series": "true",
                "ts_effect_direction": "positive"
            },
            "scores": {
                "Correlation": 9,
                "Sentiment": 7,
                "Importance": 8,
                "Impact": 7,
                "Duration": 5,
                "Entity_Density": 8,
                "Market_Scope": 6,
                "Time_Proximity": 8,
                "Headline_Structure": 7,
                "Source_Recency": 8
            }
        },
        {
            "time": "",
            "original_text": "宁德时代入股加拿大锂业公司 投资近4400万元",
            "features": {
                "keywords": [
                    "宁德时代",
                    "加拿大",
                    "锂业",
                    "投资"
                ],
                "sentiment_score": 0.7,
                "policy_related": "false",
                "investment_strategy": "true",
                "sector_focus": [
                    "新能源汽车",
                    "锂电池"
                ],
                "causal_factor": "true",
                "causal_impact": "positive",
                "affected_by_time_series": "false",
                "ts_effect_direction": ""
            },
            "scores": {
                "Correlation": 8,
                "Sentiment": 6,
                "Importance": 7,
                "Impact": 6,
                "Duration": 4,
                "Entity_Density": 7,
                "Market_Scope": 5,
                "Time_Proximity": 8,
                "Headline_Structure": 6,
                "Source_Recency": 8
            }
        },
        {
            "time": "",
            "original_text": "特斯拉板块逐级走高，拓普集团冲击涨停",
            "features": {
                "keywords": [
                    "特斯拉",
                    "板块",
                    "涨停"
                ],
                "sentiment_score": 0.8,
                "policy_related": "false",
                "investment_strategy": "false",
                "sector_focus": [
                    "新能源汽车"
                ],
                "causal_factor": "true",
                "causal_impact": "positive",
                "affected_by_time_series": "true",
                "ts_effect_direction": "positive"
            },
            "scores": {
                "Correlation": 8,
                "Sentiment": 7,
                "Importance": 7,
                "Impact": 6,
                "Duration": 4,
                "Entity_Density": 7,
                "Market_Scope": 6,
                "Time_Proximity": 8,
                "Headline_Structure": 6,
                "Source_Recency": 8
            }
        }
    ]
]