[
    [
        {
            "time": "",
            "original_text": "中国国航一季度净利27.2亿同比增长4% 现金流量净额59.4亿",
            "features": {
                "keywords": [
                    "中国国航",
                    "一季度",
                    "净利",
                    "同比增长",
                    "现金流量净额"
                ],
                "sentiment_score": 0.8,
                "policy_related": "false",
                "investment_strategy": "false",
                "sector_focus": [
                    "航空"
                ],
                "causal_factor": "true",
                "causal_impact": "positive",
                "affected_by_time_series": "true",
                "ts_effect_direction": "positive"
            },
            "scores": {
                "News_content": "中国国航一季度净利27.2亿同比增长4% 现金流量净额59.4亿",
                "Correlation": 10,
                "Sentiment": 7,
                "Importance": 8,
                "Impact": 7,
                "Duration": 6,
                "Entity_Density": 10,
                "Market_Scope": 3,
                "Time_Proximity": 9,
                "Headline_Structure": 6,
                "Source_Recency": 9
            }
        },
        {
            "time": "",
            "original_text": "中国国航:混改干扰收入增速,扣汇利润大幅增长",
            "features": {
                "keywords": [
                    "中国国航",
                    "混改",
                    "收入增速",
                    "扣汇利润",
                    "增长"
                ],
                "sentiment_score": 0.6,
                "policy_related": "true",
                "investment_strategy": "false",
                "sector_focus": [
                    "航空"
                ],
                "causal_factor": "true",
                "causal_impact": "positive",
                "affected_by_time_series": "true",
                "ts_effect_direction": "positive"
            },
            "scores": {
                "News_content": "中国国航:混改干扰收入增速,扣汇利润大幅增长",
                "Correlation": 10,
                "Sentiment": 7,
                "Importance": 8,
                "Impact": 8,
                "Duration": 7,
                "Entity_Density": 10,
                "Market_Scope": 4,
                "Time_Proximity": 8,
                "Headline_Structure": 8,
                "Source_Recency": 8
            }
        },
        {
            "time": "",
            "original_text": "中国国航:营收增长超预期,客票水平提升明显",
            "features": {
                "keywords": [
                    "中国国航",
                    "营收增长",
                    "超预期",
                    "客票水平",
                    "提升"
                ],
                "sentiment_score": 0.9,
                "policy_related": "false",
                "investment_strategy": "false",
                "sector_focus": [
                    "航空"
                ],
                "causal_factor": "true",
                "causal_impact": "positive",
                "affected_by_time_series": "true",
                "ts_effect_direction": "positive"
            },
            "scores": {
                "News_content": "中国国航:营收增长超预期,客票水平提升明显",
                "Correlation": 10,
                "Sentiment": 9,
                "Importance": 9,
                "Impact": 9,
                "Duration": 7,
                "Entity_Density": 10,
                "Market_Scope": 4,
                "Time_Proximity": 8,
                "Headline_Structure": 8,
                "Source_Recency": 8
            }
        }
    ]
]