[
    [
        {
            "time": "2023-10-01",
            "original_text": "市场轮动加快 上证50强势拉升",
            "features": {
                "keywords": [
                    "市场轮动",
                    "上证50",
                    "强势拉升"
                ],
                "sentiment_score": 0.7,
                "policy_related": "false",
                "investment_strategy": "true",
                "sector_focus": [
                    "指数",
                    "金融"
                ],
                "causal_factor": "true",
                "causal_impact": "positive",
                "affected_by_time_series": "true",
                "ts_effect_direction": "positive"
            },
            "scores": {
                "News_content": "市场轮动加快 上证50强势拉升",
                "Correlation": 7,
                "Sentiment": 8,
                "Importance": 7,
                "Impact": 8,
                "Duration": 6,
                "Entity_Density": 4,
                "Market_Scope": 9,
                "Time_Proximity": 9,
                "Headline_Structure": 7,
                "Source_Recency": 9
            }
        },
        {
            "time": "2023-10-01",
            "original_text": "生意社：“关闭”潮蔓延 钴市震荡调整",
            "features": {
                "keywords": [
                    "关闭潮",
                    "钴市",
                    "震荡调整"
                ],
                "sentiment_score": -0.6,
                "policy_related": "false",
                "investment_strategy": "false",
                "sector_focus": [
                    "有色金属",
                    "原材料"
                ],
                "causal_factor": "true",
                "causal_impact": "negative",
                "affected_by_time_series": "true",
                "ts_effect_direction": "negative"
            },
            "scores": {
                "News_content": "生意社：“关闭”潮蔓延 钴市震荡调整",
                "Correlation": 6,
                "Sentiment": 4,
                "Importance": 6,
                "Impact": 6,
                "Duration": 5,
                "Entity_Density": 5,
                "Market_Scope": 7,
                "Time_Proximity": 7,
                "Headline_Structure": 8,
                "Source_Recency": 8
            }
        },
        {
            "time": "2023-10-01",
            "original_text": "【东吴电新】宝马19年财报点评：总体平稳增长，电动化大幅加码",
            "features": {
                "keywords": [
                    "宝马",
                    "财报",
                    "平稳增长",
                    "电动化",
                    "加码"
                ],
                "sentiment_score": 0.8,
                "policy_related": "false",
                "investment_strategy": "true",
                "sector_focus": [
                    "汽车",
                    "新能源"
                ],
                "causal_factor": "true",
                "causal_impact": "positive",
                "affected_by_time_series": "false",
                "ts_effect_direction": "neutral"
            },
            "scores": {
                "News_content": "【东吴电新】宝马19年财报点评：总体平稳增长，电动化大幅加码",
                "Correlation": 8,
                "Sentiment": 7,
                "Importance": 8,
                "Impact": 7,
                "Duration": 8,
                "Entity_Density": 7,
                "Market_Scope": 6,
                "Time_Proximity": 6,
                "Headline_Structure": 9,
                "Source_Recency": 7
            }
        }
    ]
]