[
    [
        {
            "time": "",
            "original_text": "金龙鱼：公司已推出“海皇牌”料酒，主要在餐饮渠道进行销售",
            "features": {
                "keywords": [
                    "金龙鱼",
                    "海皇牌",
                    "料酒",
                    "餐饮渠道"
                ],
                "sentiment_score": 0.6,
                "policy_related": "false",
                "investment_strategy": "false",
                "sector_focus": [
                    "食品饮料"
                ],
                "causal_factor": "true",
                "causal_impact": "positive",
                "affected_by_time_series": "false",
                "ts_effect_direction": ""
            },
            "scores": {
                "News_content": "金龙鱼：公司已推出“海皇牌”料酒，主要在餐饮渠道进行销售",
                "Correlation": 9,
                "Sentiment": 6,
                "Importance": 5,
                "Impact": 4,
                "Duration": 5,
                "Entity_Density": 8,
                "Market_Scope": 3,
                "Time_Proximity": 7,
                "Headline_Structure": 6,
                "Source_Recency": 8
            }
        }
    ]
]