[
    [
        {
            "time": "",
            "original_text": "817家公司现国家队身影，白马股分歧，创蓝筹受青睐",
            "features": {
                "keywords": [
                    "国家队",
                    "白马股",
                    "创蓝筹"
                ],
                "sentiment_score": 0.6,
                "policy_related": "true",
                "investment_strategy": "true",
                "sector_focus": [
                    "金融",
                    "蓝筹股"
                ],
                "causal_factor": "true",
                "causal_impact": "positive",
                "affected_by_time_series": "false",
                "ts_effect_direction": ""
            },
            "scores": {
                "News_content": "817家公司现国家队身影，白马股分歧，创蓝筹受青睐",
                "Correlation": 8,
                "Sentiment": 6,
                "Importance": 7,
                "Impact": 7,
                "Duration": 6,
                "Entity_Density": 5,
                "Market_Scope": 9,
                "Time_Proximity": 8,
                "Headline_Structure": 8,
                "Source_Recency": 9
            }
        },
        {
            "time": "",
            "original_text": "[中性评级]航空运输行业3月数据点评：客座率出现分化 需求增速无忧",
            "features": {
                "keywords": [
                    "航空运输",
                    "客座率",
                    "需求增速"
                ],
                "sentiment_score": 0.5,
                "policy_related": "false",
                "investment_strategy": "false",
                "sector_focus": [
                    "航空"
                ],
                "causal_factor": "true",
                "causal_impact": "neutral",
                "affected_by_time_series": "true",
                "ts_effect_direction": "positive"
            },
            "scores": {
                "News_content": "[中性评级]航空运输行业3月数据点评：客座率出现分化 需求增速无忧",
                "Correlation": 7,
                "Sentiment": 5,
                "Importance": 6,
                "Impact": 5,
                "Duration": 5,
                "Entity_Density": 4,
                "Market_Scope": 8,
                "Time_Proximity": 7,
                "Headline_Structure": 6,
                "Source_Recency": 8
            }
        },
        {
            "time": "",
            "original_text": "航空行业动态：供给增速较快 客座率承压",
            "features": {
                "keywords": [
                    "航空行业",
                    "供给增速",
                    "客座率"
                ],
                "sentiment_score": 0.4,
                "policy_related": "false",
                "investment_strategy": "false",
                "sector_focus": [
                    "航空"
                ],
                "causal_factor": "true",
                "causal_impact": "negative",
                "affected_by_time_series": "true",
                "ts_effect_direction": "negative"
            },
            "scores": {
                "News_content": "航空行业动态：供给增速较快 客座率承压",
                "Correlation": 8,
                "Sentiment": 4,
                "Importance": 7,
                "Impact": 6,
                "Duration": 6,
                "Entity_Density": 5,
                "Market_Scope": 8,
                "Time_Proximity": 7,
                "Headline_Structure": 7,
                "Source_Recency": 8
            }
        },
        {
            "time": "",
            "original_text": "全年运输总周转量首次突破千亿吨公里",
            "features": {
                "keywords": [
                    "运输总周转量",
                    "突破",
                    "亿吨公里"
                ],
                "sentiment_score": 0.8,
                "policy_related": "false",
                "investment_strategy": "false",
                "sector_focus": [
                    "交通运输"
                ],
                "causal_factor": "true",
                "causal_impact": "positive",
                "affected_by_time_series": "true",
                "ts_effect_direction": "positive"
            },
            "scores": {
                "News_content": "全年运输总周转量首次突破千亿吨公里",
                "Correlation": 7,
                "Sentiment": 8,
                "Importance": 9,
                "Impact": 8,
                "Duration": 7,
                "Entity_Density": 4,
                "Market_Scope": 7,
                "Time_Proximity": 6,
                "Headline_Structure": 6,
                "Source_Recency": 7
            }
        }
    ]
]